qmvvm/__init__.py
qmvvm/computed.py
qmvvm/mvvm.py
qmvvm/proxy.py
qmvvm/ref.py
qmvvm-0.0.4.dist-info/LICENSE
qmvvm-0.0.4.dist-info/METADATA
qmvvm-0.0.4.dist-info/WHEEL
qmvvm-0.0.4.dist-info/top_level.txt
qmvvm-0.0.4.dist-info/RECORD
