Metadata-Version: 2.1
Name: QMVVM
Version: 0.0.4
Summary: A Model-View-ViewModel(MVVM) framework for Qt
Home-page: https://github.com/zhiyiYo/QMVVM
Author: zhiyiYo
Author-email: shokokawaii@outlook.com
License: Apache-2.0
Project-URL: Documentation, https://github.com/zhiyiYo/QMVVM
Project-URL: Source Code, https://github.com/zhiyiYo/QMVVM
Project-URL: Bug Tracker, https://github.com/zhiyiYo/QMVVM/issues
Keywords: qt pyqt pyside mvvm
Classifier: Programming Language :: Python :: 3
Classifier: License :: OSI Approved :: Apache Software License
Classifier: Operating System :: OS Independent
License-File: LICENSE
Requires-Dist: qtpy
